uniquepwd.py
uniquepwd-1.0.0.dist-info/DESCRIPTION.rst
uniquepwd-1.0.0.dist-info/METADATA
uniquepwd-1.0.0.dist-info/RECORD
uniquepwd-1.0.0.dist-info/WHEEL
uniquepwd-1.0.0.dist-info/entry_points.txt
uniquepwd-1.0.0.dist-info/metadata.json
uniquepwd-1.0.0.dist-info/top_level.txt
