Metadata-Version: 2.0
Name: uniquepwd
Version: 1.0.0
Summary: A module for getting short unique paths
Home-page: https://github.com/jaredwindover/uniquepwd
Author: Jared Windover
Author-email: jaredwindover@gmail.com
License: MIT
Keywords: pwd path short unique
Platform: UNKNOWN
Classifier: Development Status :: 5 - Production/Stable
Classifier: Environment :: Console
Classifier: Intended Audience :: System Administrators
Classifier: Intended Audience :: Developers
Classifier: Topic :: System :: Shells
Classifier: License :: OSI Approved :: MIT License
Classifier: Programming Language :: Python
